kafkaservice/__init__.py
kafkaservice/constant.py
kafkaservice/custom_producer.py
kafkaservice/utils.py
kafkaservice-0.1.0.dist-info/METADATA
kafkaservice-0.1.0.dist-info/WHEEL
kafkaservice-0.1.0.dist-info/top_level.txt
kafkaservice-0.1.0.dist-info/RECORD
