Metadata-Version: 2.1
Name: kafkaservice
Version: 0.1.0
Summary: Library for feeding data to kafka
Home-page: UNKNOWN
Author: VuHoang
License: MIT
Platform: UNKNOWN
